__init__.py
lrclib.py
lrclib_python-0.2.dist-info/licenses/LICENSE
lrclib_python-0.2.dist-info/METADATA
lrclib_python-0.2.dist-info/WHEEL
lrclib_python-0.2.dist-info/top_level.txt
lrclib_python-0.2.dist-info/RECORD
