Metadata-Version: 2.4
Name: lrclib-python
Version: 0.2
Summary: A pure python client for lrclib
Author-email: Enulix <kareemoidd@gmail.com>
Project-URL: Homepage, https://github.com/Enulix/lrclib-python
Classifier: Development Status :: 4 - Beta
Classifier: Programming Language :: Python :: 3
Requires-Python: >=3.8
License-File: LICENSE
Requires-Dist: requests
Dynamic: license-file
